biorxiv_fetch/__init__.py
biorxiv_fetch/core.py
biorxiv_fetch-1.0.0.dist-info/licenses/LICENSE
biorxiv_fetch-1.0.0.dist-info/METADATA
biorxiv_fetch-1.0.0.dist-info/WHEEL
biorxiv_fetch-1.0.0.dist-info/top_level.txt
biorxiv_fetch-1.0.0.dist-info/RECORD
